stealerlo_mcp/__init__.py
stealerlo_mcp/server.py
stealerlogs_mcp_server-2.0.3.dist-info/licenses/LICENSE
stealerlogs_mcp_server-2.0.3.dist-info/METADATA
stealerlogs_mcp_server-2.0.3.dist-info/WHEEL
stealerlogs_mcp_server-2.0.3.dist-info/entry_points.txt
stealerlogs_mcp_server-2.0.3.dist-info/top_level.txt
stealerlogs_mcp_server-2.0.3.dist-info/RECORD
