Metadata-Version: 2.4
Name: stealerlogs-mcp-server
Version: 2.0.3
Summary: Model Context Protocol server for Stealerlo.gs API - Integrate stealerlog search with AI assistants
Home-page: https://github.com/cryphorix/stealerlo.gs
Author: Stealerlo.gs
Author-email: "Stealerlo.gs" <support@stealerlo.gs>
License-Expression: MIT
Project-URL: Homepage, https://stealerlo.gs
Project-URL: Documentation, https://docs.stealerlo.gs/mcp
Project-URL: Repository, https://github.com/cryphorix/stealerlo.gs
Keywords: mcp,model-context-protocol,stealerlo,api,stealerlogs
Classifier: Development Status :: 4 - Beta
Classifier: Intended Audience :: Developers
Classifier: Operating System :: OS Independent
Classifier: Programming Language :: Python :: 3
Classifier: Programming Language :: Python :: 3.8
Classifier: Programming Language :: Python :: 3.9
Classifier: Programming Language :: Python :: 3.10
Classifier: Programming Language :: Python :: 3.11
Classifier: Programming Language :: Python :: 3.12
Classifier: Programming Language :: Python :: 3.13
Requires-Python: >=3.8
License-File: LICENSE
Requires-Dist: mcp>=0.9.0
Requires-Dist: httpx>=0.25.0
Requires-Dist: pydantic>=2.0.0
Dynamic: author
Dynamic: home-page
Dynamic: license-file
Dynamic: requires-python
